pcm/__init__.py
pcm/__main__.py
pcm/case_generator.py
pcm/codefile.py
pcm/config.py
pcm/config.toml
pcm/exec.py
pcm/exec_windows.py
pcm/interactive_runner.py
pcm/utils.py
pcm/cc_server/.gitignore
pcm/cc_server/__init__.py
pcm/cc_server/__main__.py
pcm/cc_server/icon.jpg
pcm/cc_server/index.js
pcm/cc_server/package.json
pcm/cc_server/yarn.lock
pcm/default_template/.vscode/launch.json
pcm/default_template/.vscode/settings.json
pcm/default_template/.vscode/tasks.json
pcm/default_template/codes/solve.cpp
pcm/default_template/codes/solve.py
pcm/default_template/test/c1.in
pcm/default_template/test/c1.out
pcm/default_template/test/gen.py
pcm/default_template/test/judge.cpp
pcm/default_template/test/judge.py
pcm/default_template/test/sample-1.in
pcm/default_template/test/sample-1.out
pcm/default_template/test/sample-2.in
pcm/default_template/test/sample-2.out
pcm/default_template/test/sample-3.in
pcm/default_template/test/sample-3.out
pcm/scripts/debug.py
pcm/scripts/prepare_all.py
pcm-0.8.1.dist-info/LICENSE
pcm-0.8.1.dist-info/METADATA
pcm-0.8.1.dist-info/WHEEL
pcm-0.8.1.dist-info/entry_points.txt
pcm-0.8.1.dist-info/top_level.txt
pcm-0.8.1.dist-info/RECORD
