Metadata-Version: 2.1
Name: pcm
Version: 0.8.1
Summary: tiny programing contest manager
Home-page: https://github.com/kjnh10/pcm
Author: kjnh10
Author-email: kojinho10@gmail.com
License: UNKNOWN
Platform: UNKNOWN
Classifier: Development Status :: 4 - Beta
Classifier: Environment :: Console
Classifier: Intended Audience :: Developers
Classifier: License :: OSI Approved :: MIT License
Classifier: Operating System :: OS Independent
Classifier: Programming Language :: Python :: 3.7
Classifier: Programming Language :: Python :: 3.8
Requires-Python: >=3.6
Requires-Dist: Click (>=7.0)
Requires-Dist: online-judge-tools (>=9.0.0)
Requires-Dist: online-judge-verify-helper
Requires-Dist: toml
Requires-Dist: pyside2
Requires-Dist: pyperclip
Provides-Extra: dev
Requires-Dist: isort (==5.5.2) ; extra == 'dev'
Requires-Dist: mypy (==0.782) ; extra == 'dev'
Requires-Dist: pylint (==2.6.0) ; extra == 'dev'
Requires-Dist: yapf (==0.30.0) ; extra == 'dev'
